{"cameraMode":{"drawMode":0,"name":"Shaded","section":"Shading Mode"},"sceneLighting":true,"audioPlay":false,"sceneViewState":{"m_AlwaysRefresh":false,"showFog":false,"showSkybox":false,"showFlares":false,"showImageEffects":false,"showParticleSystems":false,"showVisualEffectGraphs":true,"m_FxEnabled":true},"in2DMode":false,"pivot":{"x":-6.332398414611816,"y":1.1406997442245484,"z":-3.697458267211914},"rotation":{"x":0.11262161284685135,"y":-0.2813700735569,"z":0.04060529172420502,"w":0.9530290961265564},"size":0.9604997038841248,"orthographic":false}